version
updog3/__init__.py
updog3/__main__.py
updog3/static/css/bootstrap.min.css
updog3/static/css/font.scss
updog3/static/css/style.min.css
updog3/static/css/style.scss
updog3/static/fonts/poppins/poppins-v5-latin-300.eot
updog3/static/fonts/poppins/poppins-v5-latin-300.svg
updog3/static/fonts/poppins/poppins-v5-latin-300.ttf
updog3/static/fonts/poppins/poppins-v5-latin-300.woff
updog3/static/fonts/poppins/poppins-v5-latin-300.woff2
updog3/static/fonts/poppins/poppins-v5-latin-600.eot
updog3/static/fonts/poppins/poppins-v5-latin-600.svg
updog3/static/fonts/poppins/poppins-v5-latin-600.ttf
updog3/static/fonts/poppins/poppins-v5-latin-600.woff
updog3/static/fonts/poppins/poppins-v5-latin-600.woff2
updog3/static/images/Updog3.png
updog3/static/images/favicon.ico
updog3/static/images/updog.png
updog3/static/js/jquery-3.4.1.min.js
updog3/static/js/main.js
updog3/static/vendor/datatable/datatables.min.css
updog3/static/vendor/datatable/datatables.min.js
updog3/static/vendor/datatable/file-size.js
updog3/static/vendor/datatable/DataTables-1.10.18/images/sort_asc.png
updog3/static/vendor/datatable/DataTables-1.10.18/images/sort_asc_disabled.png
updog3/static/vendor/datatable/DataTables-1.10.18/images/sort_both.png
updog3/static/vendor/datatable/DataTables-1.10.18/images/sort_desc.png
updog3/static/vendor/datatable/DataTables-1.10.18/images/sort_desc_disabled.png
updog3/static/vendor/fontawesome-5.1/LICENSE.txt
updog3/static/vendor/fontawesome-5.1/css/all.min.css
updog3/static/vendor/fontawesome-5.1/webfonts/fa-brands-400.eot
updog3/static/vendor/fontawesome-5.1/webfonts/fa-brands-400.svg
updog3/static/vendor/fontawesome-5.1/webfonts/fa-brands-400.ttf
updog3/static/vendor/fontawesome-5.1/webfonts/fa-brands-400.woff
updog3/static/vendor/fontawesome-5.1/webfonts/fa-brands-400.woff2
updog3/static/vendor/fontawesome-5.1/webfonts/fa-regular-400.eot
updog3/static/vendor/fontawesome-5.1/webfonts/fa-regular-400.svg
updog3/static/vendor/fontawesome-5.1/webfonts/fa-regular-400.ttf
updog3-1.4.4.dist-info/LICENSE
updog3-1.4.4.dist-info/METADATA
updog3-1.4.4.dist-info/WHEEL
updog3-1.4.4.dist-info/entry_points.txt
updog3-1.4.4.dist-info/top_level.txt
updog3-1.4.4.dist-info/RECORD
