Metadata-Version: 2.1
Name: updog3
Version: 1.4.4
Summary: updog3 is a fork of Sc0tfree's Updog tool, which was a replacement for Python's SimpleHTTPServer. It allows uploading and downloading via HTTP/S, can set ad hoc and custom SSL certificates, use HTTP basic auth, and disable upload and download functionality when required
Home-page: https://github.com/felmoltor/updog3
Download-URL: https://github.com/felmoltor/updog3/archive/updog-1.4.4.tar.gz
Author: felmoltor
Author-email: me@felipemolina.com
License: MIT
Keywords: HTTP server SimpleHTTPServer directory
Classifier: Development Status :: 5 - Production/Stable
Classifier: Environment :: Console
Classifier: Environment :: Web Environment
Classifier: Framework :: Flask
Classifier: Intended Audience :: Developers
Classifier: Intended Audience :: System Administrators
Classifier: License :: OSI Approved :: MIT License
Classifier: Natural Language :: English
Classifier: Operating System :: MacOS
Classifier: Operating System :: Microsoft :: Windows
Classifier: Operating System :: POSIX
Classifier: Programming Language :: Python :: 3
Classifier: Programming Language :: Python :: 3.4
Classifier: Programming Language :: Python :: 3.5
Classifier: Programming Language :: Python :: 3.6
Classifier: Programming Language :: Python :: 3.7
Classifier: Programming Language :: Python :: 3.8
Classifier: Topic :: Communications :: File Sharing
Classifier: Topic :: Internet :: WWW/HTTP
Classifier: Topic :: Internet :: WWW/HTTP :: WSGI
Classifier: Topic :: Security
License-File: LICENSE
Requires-Dist: colorama
Requires-Dist: flask
Requires-Dist: flask-httpauth
Requires-Dist: werkzeug
Requires-Dist: pyopenssl
